Ejercicio5/Ejercicio5.v
module DFF_4IN(input logic [3:0] D,input logic clk,input logic async_reset,input logic sync_set,output [3:0] Q);
reg Q;
always @(posedge clk or posedge async_reset)  
begin
  if(async_reset)
   begin
   Q <= 4'b0000; 
   end
  else if(clk)
   begin
	if(sync_set==1'b1)
	begin
	  Q <= 4'b1111; 
	end
	
	else
	 begin
	  Q <= D;
	 end
   end
end 
endmodule

Ejercicio5/Ejercicio5_tb.v
module tb_DFF();
reg [3:0] D;
reg clk;
reg reset;
reg set;
wire [3:0] Q;

DFF_4IN FFP1(D,clk,reset,set,Q);

	initial begin
	  clk=0;
		 forever #10 clk = ~clk;  
	end 
	initial begin 
	   reset=0; set=0; D=4'b0000;
	#2 reset=1;
	#4 D=4'b0000;
	#6 D=4'b1111;
	#3 reset=0;
	#3 D=4'b0000;
	#6 D=4'b1111;
	#3 set=1;
	#3 D=4'b0000;
	#6 D=4'b1111;
	#3 set=0;
	#3 D=4'b0000;
	#6 D=4'b1111;
	#6 D=4'b0000;
	#6 D=4'b1111;
	#6 D=4'b0000;
	#6 D=4'b1111;
	#6 D=4'b0000;
	#6 D=4'b1111;
	#6 D=4'b0000;
	#6 D=4'b1111;
	#6 D=4'b0000;
	#6 D=4'b1111;
	#6 D=4'b0000;
	#6 D=4'b1111;
	#6 D=4'b0000;
	#6 D=4'b1111;
	#6 D=4'b0000;
	#6 D=4'b1111;
	#6 D=4'b0000;
	
	end 
	
	initial
	#155 $finish; 

	initial begin
     $dumpfile("Ejercicio5_tb.vcd");
     $dumpvars(0, tb_DFF);
    end

endmodule

Ejercicio5/Ejercicio5_tb.vcd
$date
	Sat Sep 05 08:52:34 2020
$end
$version
	Icarus Verilog
$end
$timescale
	1ps
$end
$scope module tb_DFF $end
$var wire 4 ! Q [3:0] $end
$var reg 4 " D [3:0] $end
$var reg 1 # clk $end
$var reg 1 $ reset $end
$var reg 1 % set $end
$scope module FFP1 $end
$var wire 4 & D [3:0] $end
$var wire 1 $ async_reset $end
$var wire 1 # clk $end
$var wire 1 % sync_set $end
$var reg 4 ' Q [3:0] $end
$upscope $end
$upscope $end
$enddefinitions $end
#0
$dumpvars
bx '
b0 &
0%
0$
0#
b0 "
bx !
$end
#2
b0 !
b0 '
1$
#10
1#
#12
b1111 "
b1111 &
#15
0$
#18
b0 "
b0 &
#20
0#
#24
b1111 "
b1111 &
#27
1%
#30
b1111 !
b1111 '
b0 "
b0 &
1#
#36
b1111 "
b1111 &
#39
0%
#40
0#
#42
b0 "
b0 &
#48
b1111 "
b1111 &
#50
1#
#54
b0 "
b0 &
#60
b1111 "
b1111 &
0#
#66
b0 "
b0 &
#70
b0 !
b0 '
1#
#72
b1111 "
b1111 &
#78
b0 "
b0 &
#80
0#
#84
b1111 "
b1111 &
#90
b0 "
b0 &
1#
#96
b1111 "
b1111 &
#100
0#
#102
b0 "
b0 &
#108
b1111 "
b1111 &
#110
b1111 !
b1111 '
1#
#114
b0 "
b0 &
#120
b1111 "
b1111 &
0#
#126
b0 "
b0 &
#130
b0 !
b0 '
1#
#132
b1111 "
b1111 &
#138
b0 "
b0 &
#140
0#
#144
b1111 "
b1111 &
#150
b0 "
b0 &
1#
