Ejercicio6_1/Ejercicio6_1.v
module DFF_2IN(input logic [1:0] D,input wire clk,input wire async_reset,input wire sync_set,output [1:0] Q);
reg Q;
always @(posedge clk or posedge async_reset)  
	begin
		if(async_reset)
			begin
				Q <= 2'b00; 
			end
		else if(sync_set==1'b1)
					begin
						Q <= 2'b11;
					end
		else
			begin
				Q <= D;
			end
	end
endmodule 

module BehavioralLeveling_FSM (input wire clk, async_reset, sync_set, A, B, output Y);

	wire [1:0]D;
	wire [1:0]Q;
	
	DFF_2IN FFD1(D,clk, async_reset, sync_set, Q);
	
	assign D[1] = ( Q[0] & B ) | ( Q[1] & A & B );
	assign D[0] = ~Q[1] & ~Q[0] & A;
	assign Y = Q[1] & A & B;
	
endmodule

Ejercicio6_1/Ejercicio6_1_tb.v
module tb_DFF();

reg clk, reset, set, A, B; 
reg [1:0]FS;
wire Y;

BehavioralLeveling_FSM   FMS_1(clk, reset, set, A, B, Y);

initial begin
	clk=0;
	forever #10 clk = ~clk;  
end 

initial begin

	#1 $display("");
	$display("EJERCICIO 6: EJERCICIO 1");
    $display(" A  B | FS  Y ");
    $display("-----|------------");
    $monitor(" %b  %b |  S%b   %b ", A, B, FS, Y);
	   
	   reset = 1; A = 0; B = 0; set = 0; FS = 0;
	#1 reset=0;
    #13  A = 0; B = 0; FS = 0; 
    #10  A = 0; B = 0; FS = 0; 
    #10  A = 1; B = 0; FS = 0; 
    #10  A = 1; B = 0; FS = 1;
    #10  A = 1; B = 0; FS = 1; 
    #10  A = 1; B = 0; FS = 0; 
	#10  A = 1; B = 0; FS = 0; 
    #10  A = 1; B = 1; FS = 1;
    #10  A = 1; B = 1; FS = 1; 
    #10  A = 1; B = 1; FS = 2;
	#10  A = 1; B = 1; FS = 2; 
    #10  A = 1; B = 0; FS = 0;
    #10  A = 0; B = 0; FS = 0; 
    #10  A = 0; B = 0; FS = 0;
	#10  A = 0; B = 0; FS = 0;	
	#10 $display("");
 end
	
	initial
	#180 $finish; 

	initial begin
     $dumpfile("Ejercicio6_1_tb.vcd");
     $dumpvars(0, tb_DFF);
    end

endmodule

Ejercicio6_1/Ejercicio6_1_tb.vcd
$date
	Sun Sep 06 04:39:08 2020
$end
$version
	Icarus Verilog
$end
$timescale
	1ps
$end
$scope module tb_DFF $end
$var wire 1 ! Y $end
$var reg 1 " A $end
$var reg 1 # B $end
$var reg 2 $ FS [1:0] $end
$var reg 1 % clk $end
$var reg 1 & reset $end
$var reg 1 ' set $end
$scope module FMS_1 $end
$var wire 1 " A $end
$var wire 1 # B $end
$var wire 1 ! Y $end
$var wire 1 & async_reset $end
$var wire 1 % clk $end
$var wire 1 ' sync_set $end
$var wire 2 ( Q [1:0] $end
$var wire 2 ) D [1:0] $end
$scope module FFD1 $end
$var wire 2 * D [1:0] $end
$var wire 1 & async_reset $end
$var wire 1 % clk $end
$var wire 1 ' sync_set $end
$var reg 2 + Q [1:0] $end
$upscope $end
$upscope $end
$upscope $end
$enddefinitions $end
#0
$dumpvars
bx +
bx *
bx )
bx (
x'
x&
0%
bx $
x#
x"
x!
$end
#1
b0 (
b0 +
0!
b0 )
b0 *
b0 $
0'
0#
0"
1&
#2
0&
#10
1%
#20
0%
#30
1%
#35
b1 )
b1 *
1"
#40
0%
#45
b1 $
#50
b0 )
b0 *
b1 (
b1 +
1%
#60
0%
#65
b0 $
#70
b1 )
b1 *
b0 (
b0 +
1%
#80
0%
#85
b1 $
1#
#90
b10 )
b10 *
b1 (
b1 +
1%
#100
0%
#105
b10 $
#110
1!
b10 )
b10 *
b10 (
b10 +
1%
#120
0%
#125
b0 )
b0 *
0!
b0 $
0#
#130
b1 )
b1 *
b0 (
b0 +
1%
#135
b0 )
b0 *
0"
